setup.py
distance/__init__.py
distance/models.py
distance/tests.py
distance/fixtures/tests.json
distance/management/__init__.py
distance/management/commands/__init__.py
distance/management/commands/import_zipdata.py
distance/migrations/0001_initial.py
distance/migrations/__init__.py
distance/runtests/__init__.py
distance/runtests/runtests.py
distance/runtests/settings.py
django_distance.egg-info/PKG-INFO
django_distance.egg-info/SOURCES.txt
django_distance.egg-info/dependency_links.txt
django_distance.egg-info/top_level.txt