Metadata-Version: 1.1
Name: django-distance
Version: 0.0.3
Summary: Django application to allow looking up objects by distance.
Home-page: http://github.com/simonluijk/django-distance
Author: Simon Luijk
Author-email: simon@simonluijk.com
License: BSD
Platform: UNKNOWN
Classifier: Development Status :: 4 - Beta
Classifier: Environment :: Web Environment
Classifier: Framework :: Django
Classifier: Intended Audience :: Developers
Classifier: License :: OSI Approved :: BSD License
Classifier: Operating System :: OS Independent
Classifier: Programming Language :: Python
Classifier: Programming Language :: Python :: 3
Classifier: Topic :: Internet :: WWW/HTTP
